pypk/__init__.py
pypk/__main__.py
pypk/_contents.py
pypk/_contents_test.py
pypk/config.py
pypk/core.py
pypk/main.py
pypk/version.py
pypk-0.6.0.dist-info/LICENSE
pypk-0.6.0.dist-info/METADATA
pypk-0.6.0.dist-info/WHEEL
pypk-0.6.0.dist-info/entry_points.txt
pypk-0.6.0.dist-info/top_level.txt
pypk-0.6.0.dist-info/RECORD
