Metadata-Version: 2.1
Name: pypk
Version: 0.6.0
Summary: An opinionated Python package template generator
Home-page: https://github.com/PyriteAI/pypk
Author: Miller Wilt
Author-email: miller@pyriteai.com
License: MIT
Platform: UNKNOWN
Classifier: License :: OSI Approved :: MIT License
Classifier: Programming Language :: Python :: 3
Classifier: Programming Language :: Python :: 3.6
Requires-Python: >=3.6.0
License-File: LICENSE
Requires-Dist: appdirs
Requires-Dist: typer
Requires-Dist: importlib-metadata (<4.3)
